startfile.py
startfile-1.0.0.dist-info/WHEEL
startfile-1.0.0.dist-info/METADATA
startfile-1.0.0.dist-info/RECORD
