Metadata-Version: 2.1
Name: startfile
Version: 1.0.0
Summary: hi this help from star python
Author: None
Requires-Python: >=3.10,<4.0
Classifier: Programming Language :: Python :: 3
Classifier: Programming Language :: Python :: 3.10
